toast_animation/__init__.py
toast_animation/modern_toast.py
toast_animation-0.2.1.dist-info/licenses/LICENSE
toast_animation-0.2.1.dist-info/METADATA
toast_animation-0.2.1.dist-info/WHEEL
toast_animation-0.2.1.dist-info/top_level.txt
toast_animation-0.2.1.dist-info/RECORD
