Metadata-Version: 2.4
Name: toast_animation
Version: 0.2.1
Summary: A package for creating animated toast notifications in Flet applications.
Home-page: https://github.com/louisdev12/flet_toasty.git
Author: Heckerdev
Author-email: simplelogin-newsletter.unwilling149@simplelogin.com
Classifier: Programming Language :: Python :: 3
Classifier: License :: OSI Approved :: MIT License
Classifier: Operating System :: OS Independent
Requires-Python: >=3.0
License-File: LICENSE
Requires-Dist: flet
Dynamic: author
Dynamic: author-email
Dynamic: classifier
Dynamic: description
Dynamic: description-content-type
Dynamic: home-page
Dynamic: license-file
Dynamic: requires-dist
Dynamic: requires-python
Dynamic: summary
